Workbook
Name BalanceCheck: Model!$D$155:$AA$155

Sheet Cover
M7: LinkedIn: linkedin.com/in/valeriia-evtushenko-51110a304
C9: Financial Model – Multi‑Segment F&B Business
M19: Model Checks
C21: Table of Contents | M21: Balance Sheet Unbalanced | Q21: =IF(ROUND(SUM(BalanceCheck), 2) =0,0,1) -> 0
C23: Outputs
C24: Inputs
C25: Model
T26: Do Not
C27: Model Circularity | T27: Delete
C29: Model Circularity | F29: 1 | T29: Circularity
T30: On
T31: Off
C33: © 2026 Valeriia Evtushenko
C34: All rights reserved
C35: Fictional case study, created for portfolio demonstration purposes.
C36: All data is synthetic and not based on any real company.

Sheet Outputs
B2: Outputs
I4: All figures in CAD thousands unless stated
B5: Driver Switch | D5: =Model!D4 -> 1
B8: Historical Context — Pre-Credit Facility Period (2019–2023)
I10: 2019 | J10: 2020 | K10: 2021 | L10: 2022 | M10: 2023 | N10: 2024
B12: Revenue | I12: 8000 | J12: 9200 | K12: 10500 | L12: 11900 | M12: =SUM(Model!D14:O14) -> 13060.4 | N12: =SUM(Model!P14:AA14) -> 12210.45
B13: Expenses | I13: 7600 | J13: 9500 | K13: 11800 | L13: 16000 | M13: =-(SUM(Model!D20:O20)+SUM(Model!D15:O15)) -> 22104.24 | N13: =-(SUM(Model!P20:AA20)+SUM(Model!P15:AA15)) -> 24798.27
B14: Net Income | I14: =I12-I13 -> 400 | J14: =J12-J13 -> -300 | K14: =K12-K13 -> -1300 | L14: =L12-L13 -> -4100 | M14: =SUM(Model!D28:O28)-M15 -> -10681.515 | N14: =SUM(Model!P28:AA28)-N15 -> -15880.69
B15: Government Grants | I15: 800 | J15: 900 | K15: 1000 | L15: 1100 | M15: =Inputs!D19 -> 1800 | N15: =Inputs!E19 -> 1200
B20: Revenue vs. Total Expenses | J20: Total Net Income vs. Government Grants
B39: Historical analysis (2019–2022) shows that the company was unprofitable every year before the revolver was introduced. Grants temporarily covered the gap, but by 2023 the shortfall exceeded available funding, forcing the company to rely on debt.
B42: P&L and Cash Flow Waterfall Bridges
I44: 2024 | O44: 2024
B46: Revenue | I46: =SUM(Model!$P$14:$AA$14) -> 12210.45 | K46: Net Income | O46: =SUM(Model!P28:AA28) -> -14680.69
B47: COGS | I47: =SUM(Model!$P$15:$AA$15) -> -7326.27 | K47: Depreciation & Amortization | O47: =-SUM(Model!P23:AA23) -> 500
B48: Operation Expenses | I48: =SUM(Model!$P$20:$AA$20) -> -17472 | K48: Capital Expenditures | O48: =-SUM(Model!$P$104:$AA$104) -> 610.5225
B49: EBITDA | I49: =SUM(I46:I48) -> -12587.82 | K49: Change in Net Working Capital | O49: =SUM(Model!$P$98:$AA$98)+SUM(Model!$P$99:$AA$99)+SUM(Model!$P$100:$AA$100) -> 13.822603
B50: Depreciation & Amortization | I50: =SUM(Model!P23:AA23) -> -500 | K50: Government Grants | O50: =SUM(Model!$P$27:$AA$27) -> 1200
B51: EBIT | I51: =SUM(I49:I50) -> -13087.82 | K51: Revolver Draw (net) | O51: =SUM(Model!P111:AA111) -> 9012.2078
B52: Interest | I52: =SUM(Model!P26:AA26) -> -2792.8698 | K52: Term Loan Principal Payment | O52: =-SUM(Model!P110:AA110) -> 941.09826
B53: Net Income | I53: =SUM(I51:I52) -> -15880.69 | K53: Net Change in Cash | O53: =$O$46+$O$47-$O$48+$O$49+$O$50+$O$51-$O$52 -> -5506.2802
B57: 2024 P&L Waterfall Bridge | L57: 2024 Cash Flow Waterfall Bridge
B80: Operating expenses and interest now exceed total revenue, driving a deeper structural deficit than previously modeled — the business does not generate enough cash from operations to sustain itself.
B83: Cash flow analysis
D85: =Model!D8 -> 44927 | E85: =Model!E8 -> 44958 | F85: =Model!F8 -> 44986 | G85: =Model!G8 -> 45017 | H85: =Model!H8 -> 45047 | I85: =Model!I8 -> 45078 | J85: =Model!J8 -> 45108 | K85: =Model!K8 -> 45139 | ... AA85: =Model!AA8 -> 45627
B87: Ending Cash | D87: 500 | E87: =Model!E117 -> 500 | F87: =Model!F117 -> 500 | G87: =Model!G117 -> 500 | H87: =Model!H117 -> 500 | I87: =Model!I117 -> 500 | J87: =Model!J117 -> 500 | K87: =Model!K117 -> 500 | L87: =Model!L117 -> 500 | ... AA87: =Model!AA117 -> -6206.2802
B88: Revolver Balance | D88: =Model!D201 -> 1748.7363 | E88: =Model!E201 -> 2471.6505 | F88: =Model!F201 -> 3215.8547 | G88: =Model!G201 -> 3983.3489 | H88: =Model!H201 -> 4774.1331 | I88: =Model!I201 -> 5588.2073 | J88: =Model!J201 -> 6425.5715 | K88: =Model!K201 -> 7286.2258 | ... AA88: =Model!AA201 -> 20000
B89: Minimum Cash | D89: 500 | E89: 500 | F89: 500 | G89: 500 | H89: 500 | I89: 500 | J89: 500 | K89: 500 | L89: 500 | M89: 500 | N89: 500 | O89: 500 | P89: 500 | Q89: 500 | R89: 500 | S89: 500 | T89: 500 | U89: 500 | V89: 500 | W89: 500 | X89: 500 | Y89: 500 | Z89: 500 | AA89: 500
B113: The revolver reaches its limit of 20,000 in August 2024 — four months earlier than initially modeled. From that point, cash covenant breaches occur immediately, as the company has no remaining capacity to draw on the revolver to cover the shortfall.
B117: Debt / EBITDA (Leverage Ratio)
D119: =Model!D8 -> 44927 | E119: =Model!E8 -> 44958 | F119: =Model!F8 -> 44986 | G119: =Model!G8 -> 45017 | H119: =Model!H8 -> 45047 | I119: =Model!I8 -> 45078 | J119: =Model!J8 -> 45108 | K119: =Model!K8 -> 45139 | ... AA119: =Model!AA8 -> 45627
B121: Total Debt | D121: =Model!D142+Model!D139 -> 6676.8927 | E121: =Model!E142+Model!E139 -> 7327.6031 | F121: =Model!F142+Model!F139 -> 7999.2417 | G121: =Model!G142+Model!G139 -> 8693.8065 | H121: =Model!H142+Model!H139 -> 9411.2958 | I121: =Model!I142+Model!I139 -> 10151.708 | J121: =Model!J142+Model!J139 -> 10915.04 | K121: =Model!K142+Model!K139 -> 11701.292 | ... AA121: =Model!AA142+Model!AA139 -> 23172.609
B122: Annualized EBITDA | D122: =Model!D21*12 -> -8218.2 | E122: =Model!E21*12 -> -8365.32 | F122: =Model!F21*12 -> -8512.44 | G122: =Model!G21*12 -> -8659.56 | H122: =Model!H21*12 -> -8806.68 | I122: =Model!I21*12 -> -8953.8 | J122: =Model!J21*12 -> -9100.92 | K122: =Model!K21*12 -> -9248.04 | ... AA122: =Model!AA21*12 -> -14411.28
B123: Leverage Ratio | D123: =D121/D122 -> -0.81245195 | E123: =E121/E122 -> -0.87595013 | F123: =F121/F122 -> -0.93971196 | G123: =G121/G122 -> -1.0039548 | H123: =H121/H122 -> -1.0686542 | I123: =I121/I122 -> -1.1337876 | J123: =J121/J122 -> -1.1993337 | K123: =K121/K122 -> -1.2652726 | ... AA123: =AA121/AA122 -> -1.6079494
B142: Sensitivity Analysis
B144: NPV | E144: =XNPV(F144,Model!$D$107:$AA$107,Model!$D$8:$AA$8) -> -21292.396 | F144: =ROUNDDOWN(Model!E248,3) -> 0.111
B145: IRR | E145: =IFERROR(XIRR(Model!$D$107:$AA$107,Model!$D$8:$AA$8),"na") -> na
B146: Cash Runway | E146: =Model!$AA$117/(-Model!$D$107:$AA$107) -> -9.5376983
B147: Final Cash Balance | E147: =Model!$AA$117 -> -6206.2802
B148: Government Grants | E148: =Inputs!E19 -> 1200
B149: *n/a — all periods generate negative cash flow, so no IRR solution exists
E151: NPV Sensitivity
D152: Discount Rate
C153: =E144 -> -21292.396 | D153: 0.25 | E153: 0.15 | F153: 0.111 | G153: 0.1 | H153: 0.05
B154: Government Grants | C154: 0 | D154: =D$160+($C154-Inputs!$E$20)*D$161 -> -29228.564 | E154: =E$160+($C154-Inputs!$E$20)*E$161 -> -32277.309 | F154: =F$160+($C154-Inputs!$E$20)*F$161 -> -33648.768 | G154: =G$160+($C154-Inputs!$E$20)*G$161 -> -34057.057 | H154: =H$160+($C154-Inputs!$E$20)*H$161 -> -36045.285
C155: 500 | D155: =D$160+($C155-Inputs!$E$20)*D$161 -> -24886.346 | E155: =E$160+($C155-Inputs!$E$20)*E$161 -> -27379.754 | F155: =F$160+($C155-Inputs!$E$20)*F$161 -> -28500.279 | G155: =G$160+($C155-Inputs!$E$20)*G$161 -> -28833.743 | H155: =H$160+($C155-Inputs!$E$20)*H$161 -> -30456.843
C156: 1200 | D156: =D$160+($C156-Inputs!$E$20)*D$161 -> -18807.24 | E156: =E$160+($C156-Inputs!$E$20)*E$161 -> -20523.178 | F156: =F$160+($C156-Inputs!$E$20)*F$161 -> -21292.396 | G156: =G$160+($C156-Inputs!$E$20)*G$161 -> -21521.102 | H156: =H$160+($C156-Inputs!$E$20)*H$161 -> -22633.024
C157: 1800 | D157: =D$160+($C157-Inputs!$E$20)*D$161 -> -13596.578 | E157: =E$160+($C157-Inputs!$E$20)*E$161 -> -14646.113 | F157: =F$160+($C157-Inputs!$E$20)*F$161 -> -15114.21 | G157: =G$160+($C157-Inputs!$E$20)*G$161 -> -15253.124 | H157: =H$160+($C157-Inputs!$E$20)*H$161 -> -15926.893
C158: 2000 | D158: =D$160+($C158-Inputs!$E$20)*D$161 -> -11859.69 | E158: =E$160+($C158-Inputs!$E$20)*E$161 -> -12687.092 | F158: =F$160+($C158-Inputs!$E$20)*F$161 -> -13054.814 | G158: =G$160+($C158-Inputs!$E$20)*G$161 -> -13163.798 | H158: =H$160+($C158-Inputs!$E$20)*H$161 -> -13691.516
C159: 2400 | D159: =D$160+($C159-Inputs!$E$20)*D$161 -> -8385.9153 | E159: =E$160+($C159-Inputs!$E$20)*E$161 -> -8769.0482 | F159: =F$160+($C159-Inputs!$E$20)*F$161 -> -8936.0239 | G159: =G$160+($C159-Inputs!$E$20)*G$161 -> -8985.1466 | H159: =H$160+($C159-Inputs!$E$20)*H$161 -> -9220.7628
D160: =SUMPRODUCT(Model!$D$107:$AA$107/(1+D$153)^((Model!$D$8:$AA$8-Model!$D$8)/365)) -> -18807.24 | E160: =SUMPRODUCT(Model!$D$107:$AA$107/(1+E$153)^((Model!$D$8:$AA$8-Model!$D$8)/365)) -> -20523.178 | F160: =SUMPRODUCT(Model!$D$107:$AA$107/(1+F$153)^((Model!$D$8:$AA$8-Model!$D$8)/365)) -> -21292.396 | G160: =SUMPRODUCT(Model!$D$107:$AA$107/(1+G$153)^((Model!$D$8:$AA$8-Model!$D$8)/365)) -> -21521.102 | H160: =SUMPRODUCT(Model!$D$107:$AA$107/(1+H$153)^((Model!$D$8:$AA$8-Model!$D$8)/365)) -> -22633.024
D161: =SUMPRODUCT((YEAR(Model!$D$8:$AA$8)=2024)/(1+D$153)^((Model!$D$8:$AA$8-Model!$D$8)/365)) -> 8.6844371 | E161: =SUMPRODUCT((YEAR(Model!$D$8:$AA$8)=2024)/(1+E$153)^((Model!$D$8:$AA$8-Model!$D$8)/365)) -> 9.7951085 | F161: =SUMPRODUCT((YEAR(Model!$D$8:$AA$8)=2024)/(1+F$153)^((Model!$D$8:$AA$8-Model!$D$8)/365)) -> 10.296977 | G161: =SUMPRODUCT((YEAR(Model!$D$8:$AA$8)=2024)/(1+G$153)^((Model!$D$8:$AA$8-Model!$D$8)/365)) -> 10.446629 | H161: =SUMPRODUCT((YEAR(Model!$D$8:$AA$8)=2024)/(1+H$153)^((Model!$D$8:$AA$8-Model!$D$8)/365)) -> 11.176884
B162: At WACC = 11.1%, NPV remains negative across the entire sensitivity grid — every combination of discount rate (5%–25%) and government grants (0–2,400) tested. The business does not generate a viable return under any modeled scenario within its current cost and capital structure.
B165: EBITDA Analysis by Segments in 2024 | K165: Analysis by Segments in 2024
E167: Revenue | F167: COGS | G167: Oper. Exp. | H167: EBITDA
B169: Italian Restaurant | E169: =SUM(Model!$P$35:$AA$35) -> 2686.299 | F169: =-SUM(Model!P46:AA46) -> 1831.5675 | G169: =-SUM(Model!P68:AA68) -> 4542.72 | H169: =E169-F169-G169 -> -3687.9885
B170: Japanese Restaurant | E170: =SUM(Model!$P$36:$AA$36) -> 2075.7765 | F170: =-SUM(Model!P47:AA47) -> 1318.7286 | G170: =-SUM(Model!P69:AA69) -> 3319.68 | H170: =E170-F170-G170 -> -2562.6321
B171: Burger Joint | E171: =SUM(Model!$P$37:$AA$37) -> 2197.881 | F171: =-SUM(Model!P48:AA48) -> 1465.254 | G171: =-SUM(Model!P70:AA70) -> 2970.24 | H171: =E171-F171-G171 -> -2237.613
B172: Pizzeria | E172: =SUM(Model!$P$38:$AA$38) -> 1831.5675 | F172: =-SUM(Model!P49:AA49) -> 1025.6778 | G172: =-SUM(Model!P71:AA71) -> 2446.08 | H172: =E172-F172-G172 -> -1640.1903
B173: Beverage Brand | E173: =SUM(Model!$P$39:$AA$39) -> 1587.3585 | F173: =-SUM(Model!P50:AA50) -> 586.1016 | G173: =-SUM(Model!P72:AA72) -> 1747.2 | H173: =E173-F173-G173 -> -745.9431
B174: Delivery Service | E174: =SUM(Model!$P$40:$AA$40) -> 1831.5675 | F174: =-SUM(Model!P51:AA51) -> 879.1524 | G174: =-SUM(Model!P73:AA73) -> 2096.64 | H174: =E174-F174-G174 -> -1144.2249
B175: Central Kitchen (Commissary) | E175: =SUM(Model!$P$41:$AA$41) -> 0 | F175: =-SUM(Model!P52:AA52) -> 219.7881 | G175: =-SUM(Model!P74:AA74) -> 349.44 | H175: =E175-F175-G175 -> -569.2281
B177: Note: Analysis performed at EBITDA level (Revenue − COGS − OpEx) because D&A, interest,
B178: and grants are company-wide items without a clean segment-level allocation basis.
B179: This isolates operating performance per segment from financing/capital-structure decisions made at the corporate level.
B180: at the corporate level.
B186: All 7 segments are unprofitable. The largest EBITDA losses come from Italian Restaurant (3,688) and Japanese Restaurant (2,563). Central Kitchen shows the smallest EBITDA loss (569), but this reflects its role as an internal cost center with no external revenue, not genuine profitability. Among revenue-generating segments, Beverage Brand performs best, losing 746. This indicates a structural problem — not just one or two weak segments.

Sheet Inputs
B2: Drivers | G2: Tax Assumption Note:
G3: No income tax is included in this model because the company generates negative Net Income in all periods (2023–2024), resulting in zero taxable income.
B4: All figures in CAD thousands unless stated | D4: 2023 | E4: 2024 | G4: For reference, the combined corporate tax rate in Nova Scotia is approximately 29% (15% federal + 14% provincial)
G5: In a real‑world model with positive earnings, I would add an income tax line between EBIT and Net Income and adjust the cash flow statement accordingly.
B6: Driver Switch | C6: =Model!D4 -> 1
B9: Revenue Growth | D9: =CHOOSE($C$6,D10,D11,D12) -> 0.03 | E9: =CHOOSE($C$6,E10,E11,E12) -> 0.015
B10: Base Case | D10: 0.03 | E10: 0.015
B11: Upside case | D11: 0.05 | E11: 0.035
B12: Downside Case | D12: 0.01 | E12: -0.01
B14: Expense Growth | D14: =CHOOSE($C$6,D15,D16,D17) -> 0.025 | E14: =CHOOSE($C$6,E15,E16,E17) -> 0.04
B15: Base Case | D15: 0.025 | E15: 0.04
B16: Upside case | D16: 0.015 | E16: 0.02
B17: Downside Case | D17: 0.04 | E17: 0.055
B19: Government Grants | D19: =CHOOSE($C$6,D20,D21,D22) -> 1800 | E19: =CHOOSE($C$6,E20,E21,E22) -> 1200
B20: Base Case | D20: =150*12 -> 1800 | E20: =100*12 -> 1200
B21: Upside case | D21: =200*12 -> 2400 | E21: =200*12 -> 2400
B22: Downside Case | D22: 0 | E22: 0
B25: Fixed Assumption
B27: Minimum Cash Covenant (Revolver Trigger) | C27: 500
B28: Annua lInterest Rate on Credit Line | C28: 0.15
B29: Revolver Limit | C29: 20000
B31: Long-Term Debt Assumption
B33: Loan Amount | C33: 5000
B34: Term | C34: 5
B35: Annual Interest Rate | C35: 0.06
B37: Useful life of Assets
B39: Useful life of Assets (years) | C39: 10
B41: Operation Working Capital Assumption
B43: AR days | C43: 15
B44: AP days | C44: 20
B45: Inventory days | C45: 10
B46: Capex % of Revenue | C46: 0.05
B48: Segment Revenue Mix
B50: Italian Restaurant | D50: =CHOOSE($C$6,D51,D52,D53) -> 0.25 | E50: =CHOOSE($C$6,E51,E52,E53) -> 0.22
B51: Base Case | D51: 0.25 | E51: 0.22
B52: Upside case | D52: 0.26 | E52: 0.24
B53: Downside Case | D53: 0.2 | E53: 0.18
B55: Japanese Restaurant | D55: =CHOOSE($C$6,D56,D57,D58) -> 0.2 | E55: =CHOOSE($C$6,E56,E57,E58) -> 0.17
B56: Base Case | D56: 0.2 | E56: 0.17
B57: Upside case | D57: 0.21 | E57: 0.2
B58: Downside Case | D58: 0.15 | E58: 0.13
B60: Burger Joint | D60: =CHOOSE($C$6,D61,D62,D63) -> 0.18 | E60: =CHOOSE($C$6,E61,E62,E63) -> 0.18
B61: Base Case | D61: 0.18 | E61: 0.18
B62: Upside case | D62: 0.18 | E62: 0.18
B63: Downside Case | D63: 0.2 | E63: 0.22
B65: Pizzeria | D65: =CHOOSE($C$6,D66,D67,D68) -> 0.15 | E65: =CHOOSE($C$6,E66,E67,E68) -> 0.15
B66: Base Case | D66: 0.15 | E66: 0.15
B67: Upside case | D67: 0.15 | E67: 0.15
B68: Downside Case | D68: 0.18 | E68: 0.2
B70: Beverage Brand | D70: =CHOOSE($C$6,D71,D72,D73) -> 0.12 | E70: =CHOOSE($C$6,E71,E72,E73) -> 0.13
B71: Base Case | D71: 0.12 | E71: 0.13
B72: Upside case | D72: 0.12 | E72: 0.13
B73: Downside Case | D73: 0.12 | E73: 0.12
B75: Delivery Service | D75: =CHOOSE($C$6,D76,D77,D78) -> 0.1 | E75: =CHOOSE($C$6,E76,E77,E78) -> 0.15
B76: Base Case | D76: 0.1 | E76: 0.15
B77: Upside case | D77: 0.08 | E77: 0.1
B78: Downside Case | D78: 0.15 | E78: 0.15
B80: Central Kitchen (Commissary) | D80: =CHOOSE($C$6,D81,D82,D83) -> 0 | E80: =CHOOSE($C$6,E81,E82,E83) -> 0
B81: Base Case | D81: 0 | E81: 0
B82: Upside case | D82: 0 | E82: 0
B83: Downside Case | D83: 0 | E83: 0
B85: Base Case | D85: =D51+D56+D61+D66+D71+D76+D81 -> 1 | E85: =E51+E56+E61+E66+E71+E76+E81 -> 1
B86: Upside case | D86: =D52+D57+D62+D67+D72+D77+D82 -> 1 | E86: =E52+E57+E62+E67+E72+E77+E82 -> 1
B87: Downside Case | D87: =D53+D58+D63+D68+D73+D78+D83 -> 1 | E87: =E53+E58+E63+E68+E73+E78+E83 -> 1
B89: Segment COGS Mix
B91: Italian Restaurant | D91: =CHOOSE($C$6,D92,D93,D94) -> 0.27 | E91: =CHOOSE($C$6,E92,E93,E94) -> 0.25
B92: Base Case | D92: 0.27 | E92: 0.25
B93: Upside case | D93: 0.25 | E93: 0.23
B94: Downside Case | D94: 0.29 | E94: 0.27
B96: Japanese Restaurant | D96: =CHOOSE($C$6,D97,D98,D99) -> 0.2 | E96: =CHOOSE($C$6,E97,E98,E99) -> 0.18
B97: Base Case | D97: 0.2 | E97: 0.18
B98: Upside case | D98: 0.19 | E98: 0.17
B99: Downside Case | D99: 0.21 | E99: 0.19
B101: Burger Joint | D101: =CHOOSE($C$6,D102,D103,D104) -> 0.18 | E101: =CHOOSE($C$6,E102,E103,E104) -> 0.2
B102: Base Case | D102: 0.18 | E102: 0.2
B103: Upside case | D103: 0.17 | E103: 0.18
B104: Downside Case | D104: 0.19 | E104: 0.21
B106: Pizzeria | D106: =CHOOSE($C$6,D107,D108,D109) -> 0.14 | E106: =CHOOSE($C$6,E107,E108,E109) -> 0.14
B107: Base Case | D107: 0.14 | E107: 0.14
B108: Upside case | D108: 0.14 | E108: 0.14
B109: Downside Case | D109: 0.14 | E109: 0.14
B111: Beverage Brand | D111: =CHOOSE($C$6,D112,D113,D114) -> 0.09 | E111: =CHOOSE($C$6,E112,E113,E114) -> 0.08
B112: Base Case | D112: 0.09 | E112: 0.08
B113: Upside case | D113: 0.1 | E113: 0.1
B114: Downside Case | D114: 0.08 | E114: 0.07
B116: Delivery Service | D116: =CHOOSE($C$6,D117,D118,D119) -> 0.09 | E116: =CHOOSE($C$6,E117,E118,E119) -> 0.12
B117: Base Case | D117: 0.09 | E117: 0.12
B118: Upside case | D118: 0.11 | E118: 0.14
B119: Downside Case | D119: 0.07 | E119: 0.1
B121: Central Kitchen (Commissary) | D121: =CHOOSE($C$6,D122,D123,D124) -> 0.03 | E121: =CHOOSE($C$6,E122,E123,E124) -> 0.03
B122: Base Case | D122: 0.03 | E122: 0.03
B123: Upside case | D123: 0.04 | E123: 0.04
B124: Downside Case | D124: 0.02 | E124: 0.02
B126: Base Case | D126: =D92+D97+D102+D107+D112+D117+D122 -> 1 | E126: =E92+E97+E102+E107+E112+E117+E122 -> 1
B127: Upside case | D127: =D93+D98+D103+D108+D113+D118+D123 -> 1 | E127: =E93+E98+E103+E108+E113+E118+E123 -> 1
B128: Downside Case | D128: =D94+D99+D104+D109+D114+D119+D124 -> 1 | E128: =E94+E99+E104+E109+E114+E119+E124 -> 1
B130: Segment Expenses Mix
B132: Italian Restaurant | D132: =CHOOSE($C$6,D133,D134,D135) -> 0.28 | E132: =CHOOSE($C$6,E133,E134,E135) -> 0.26
B133: Base Case | D133: 0.28 | E133: 0.26
B134: Upside case | D134: 0.29 | E134: 0.27
...

Sheet Model
B2: Model
B4: =Inputs!B6 -> Driver Switch | D4: 1 | F4: All figures in CAD thousands unless stated
B8: Year 2023-2024 | D8: 44927 | E8: 44958 | F8: 44986 | G8: 45017 | H8: 45047 | I8: 45078 | J8: 45108 | K8: 45139 | L8: 45170 | M8: 45200 | N8: 45231 | O8: 45261 | P8: 45292 | Q8: 45323 | R8: 45352 | S8: 45383 | T8: 45413 | U8: 45444 | V8: 45474 | W8: 45505 | X8: 45536 | Y8: 45566 | Z8: 45597 | AA8: 45627
B10: Income Statement
B12: Revenue Growth | D12: =IF(YEAR(D$8)=2023,Inputs!$D$9,Inputs!$E$9) -> 0.03 | E12: =IF(YEAR(E$8)=2023,Inputs!$D$9,Inputs!$E$9) -> 0.03 | F12: =IF(YEAR(F$8)=2023,Inputs!$D$9,Inputs!$E$9) -> 0.03 | G12: =IF(YEAR(G$8)=2023,Inputs!$D$9,Inputs!$E$9) -> 0.03 | H12: =IF(YEAR(H$8)=2023,Inputs!$D$9,Inputs!$E$9) -> 0.03 | I12: =IF(YEAR(I$8)=2023,Inputs!$D$9,Inputs!$E$9) -> 0.03 | J12: =IF(YEAR(J$8)=2023,Inputs!$D$9,Inputs!$E$9) -> 0.03 | K12: =IF(YEAR(K$8)=2023,Inputs!$D$9,Inputs!$E$9) -> 0.03 | ... AA12: =IF(YEAR(AA$8)=2023,Inputs!$D$9,Inputs!$E$9) -> 0.015
B13: Base Revenue (generated) | D13: 950 | E13: 970 | F13: 990 | G13: 1010 | H13: 1030 | I13: 1050 | J13: 1070 | K13: 1090 | L13: 1110 | M13: 1130 | N13: 1150 | O13: 1130 | P13: 1110 | Q13: 1090 | R13: 1070 | S13: 1050 | T13: 1030 | U13: 1010 | V13: 990 | W13: 970 | X13: 950 | Y13: 930 | Z13: 920 | AA13: 910
B14: Revenue | D14: =D13*(D12+1) -> 978.5 | E14: =E13*(E12+1) -> 999.1 | F14: =F13*(F12+1) -> 1019.7 | G14: =G13*(G12+1) -> 1040.3 | H14: =H13*(H12+1) -> 1060.9 | I14: =I13*(I12+1) -> 1081.5 | J14: =J13*(J12+1) -> 1102.1 | K14: =K13*(K12+1) -> 1122.7 | ... AA14: =AA13*(AA12+1) -> 923.65
B15: COGS | D15: =-D14*60% -> -587.1 | E15: =-E14*60% -> -599.46 | F15: =-F14*60% -> -611.82 | G15: =-G14*60% -> -624.18 | H15: =-H14*60% -> -636.54 | I15: =-I14*60% -> -648.9 | J15: =-J14*60% -> -661.26 | K15: =-K14*60% -> -673.62 | ... AA15: =-AA14*60% -> -554.19
B16: Gross Profit | D16: =D14+D15 -> 391.4 | E16: =E14+E15 -> 399.64 | F16: =F14+F15 -> 407.88 | G16: =G14+G15 -> 416.12 | H16: =H14+H15 -> 424.36 | I16: =I14+I15 -> 432.6 | J16: =J14+J15 -> 440.84 | K16: =K14+K15 -> 449.08 | ... AA16: =AA14+AA15 -> 369.46
B18: Expenses Growth | D18: =IF(YEAR(D$8)=2023,Inputs!$D$14,Inputs!$E$14) -> 0.025 | E18: =IF(YEAR(E$8)=2023,Inputs!$D$14,Inputs!$E$14) -> 0.025 | F18: =IF(YEAR(F$8)=2023,Inputs!$D$14,Inputs!$E$14) -> 0.025 | G18: =IF(YEAR(G$8)=2023,Inputs!$D$14,Inputs!$E$14) -> 0.025 | H18: =IF(YEAR(H$8)=2023,Inputs!$D$14,Inputs!$E$14) -> 0.025 | I18: =IF(YEAR(I$8)=2023,Inputs!$D$14,Inputs!$E$14) -> 0.025 | J18: =IF(YEAR(J$8)=2023,Inputs!$D$14,Inputs!$E$14) -> 0.025 | K18: =IF(YEAR(K$8)=2023,Inputs!$D$14,Inputs!$E$14) -> 0.025 | ... AA18: =IF(YEAR(AA$8)=2023,Inputs!$D$14,Inputs!$E$14) -> 0.04
B19: Base Expenses (generated) | D19: -1050 | E19: -1070 | F19: -1090 | G19: -1110 | H19: -1130 | I19: -1150 | J19: -1170 | K19: -1190 | L19: -1210 | M19: -1230 | N19: -1250 | O19: -1270 | P19: -1290 | Q19: -1310 | R19: -1330 | S19: -1350 | T19: -1370 | U19: -1390 | V19: -1410 | W19: -1430 | X19: -1450 | Y19: -1470 | Z19: -1490 | AA19: -1510
B20: Operating Expenses | D20: =D19*(D18+1) -> -1076.25 | E20: =E19*(E18+1) -> -1096.75 | F20: =F19*(F18+1) -> -1117.25 | G20: =G19*(G18+1) -> -1137.75 | H20: =H19*(H18+1) -> -1158.25 | I20: =I19*(I18+1) -> -1178.75 | J20: =J19*(J18+1) -> -1199.25 | K20: =K19*(K18+1) -> -1219.75 | ... AA20: =AA19*(AA18+1) -> -1570.4
B21: EBITDA | D21: =D20+D16 -> -684.85 | E21: =E20+E16 -> -697.11 | F21: =F20+F16 -> -709.37 | G21: =G20+G16 -> -721.63 | H21: =H20+H16 -> -733.89 | I21: =I20+I16 -> -746.15 | J21: =J20+J16 -> -758.41 | K21: =K20+K16 -> -770.67 | ... AA21: =AA20+AA16 -> -1200.94
B23: Depreciation & Amortization | D23: =-Inputs!$C$33/(Inputs!$C$39*12) -> -41.666667 | E23: =-Inputs!$C$33/(Inputs!$C$39*12) -> -41.666667 | F23: =-Inputs!$C$33/(Inputs!$C$39*12) -> -41.666667 | G23: =-Inputs!$C$33/(Inputs!$C$39*12) -> -41.666667 | H23: =-Inputs!$C$33/(Inputs!$C$39*12) -> -41.666667 | I23: =-Inputs!$C$33/(Inputs!$C$39*12) -> -41.666667 | J23: =-Inputs!$C$33/(Inputs!$C$39*12) -> -41.666667 | K23: =-Inputs!$C$33/(Inputs!$C$39*12) -> -41.666667 | ... AA23: =-Inputs!$C$33/(Inputs!$C$39*12) -> -41.666667
B24: EBIT | D24: =SUM(D21:D23) -> -726.51667 | E24: =SUM(E21:E23) -> -738.77667 | F24: =SUM(F21:F23) -> -751.03667 | G24: =SUM(G21:G23) -> -763.29667 | H24: =SUM(H21:H23) -> -775.55667 | I24: =SUM(I21:I23) -> -787.81667 | J24: =SUM(J21:J23) -> -800.07667 | K24: =SUM(K21:K23) -> -812.33667 | ... AA24: =SUM(AA21:AA23) -> -1242.6067
B26: Interest | D26: =-D176-D206 -> -36.820391 | E26: =-E176-E206 -> -52.460273 | F26: =-F176-F206 -> -60.098349 | G26: =-G176-G206 -> -69.734611 | H26: =-H176-H206 -> -79.369051 | I26: =-I176-I206 -> -89.001657 | J26: =-J176-J206 -> -98.632422 | K26: =-K176-K206 -> -108.26134 | ... AA26: =-AA176-AA206 -> -266.06454
B27: Government Grants | D27: =IF(YEAR(D$8)=2023,Inputs!$D$19/12,Inputs!$E$19/12) -> 150 | E27: =IF(YEAR(E$8)=2023,Inputs!$D$19/12,Inputs!$E$19/12) -> 150 | F27: =IF(YEAR(F$8)=2023,Inputs!$D$19/12,Inputs!$E$19/12) -> 150 | G27: =IF(YEAR(G$8)=2023,Inputs!$D$19/12,Inputs!$E$19/12) -> 150 | H27: =IF(YEAR(H$8)=2023,Inputs!$D$19/12,Inputs!$E$19/12) -> 150 | I27: =IF(YEAR(I$8)=2023,Inputs!$D$19/12,Inputs!$E$19/12) -> 150 | J27: =IF(YEAR(J$8)=2023,Inputs!$D$19/12,Inputs!$E$19/12) -> 150 | K27: =IF(YEAR(K$8)=2023,Inputs!$D$19/12,Inputs!$E$19/12) -> 150 | ... AA27: =IF(YEAR(AA$8)=2023,Inputs!$D$19/12,Inputs!$E$19/12) -> 100
B28: Net Income | D28: =D24+D26+D27 -> -613.33706 | E28: =E24+E26+E27 -> -641.23694 | F28: =F24+F26+F27 -> -661.13502 | G28: =G24+G26+G27 -> -683.03128 | H28: =H24+H26+H27 -> -704.92572 | I28: =I24+I26+I27 -> -726.81832 | J28: =J24+J26+J27 -> -748.70909 | K28: =K24+K26+K27 -> -770.598 | ... AA28: =AA24+AA26+AA27 -> -1408.6712
B31: Segment P&L (breakdown by business units)
B33: Revenue by Segment
B35: Italian Restaurant | D35: =D$14*(IF(YEAR(D$8)=2023,Inputs!$D$50,Inputs!$E$50)) -> 244.625 | E35: =E$14*(IF(YEAR(E$8)=2023,Inputs!$D$50,Inputs!$E$50)) -> 249.775 | F35: =F$14*(IF(YEAR(F$8)=2023,Inputs!$D$50,Inputs!$E$50)) -> 254.925 | G35: =G$14*(IF(YEAR(G$8)=2023,Inputs!$D$50,Inputs!$E$50)) -> 260.075 | H35: =H$14*(IF(YEAR(H$8)=2023,Inputs!$D$50,Inputs!$E$50)) -> 265.225 | I35: =I$14*(IF(YEAR(I$8)=2023,Inputs!$D$50,Inputs!$E$50)) -> 270.375 | J35: =J$14*(IF(YEAR(J$8)=2023,Inputs!$D$50,Inputs!$E$50)) -> 275.525 | K35: =K$14*(IF(YEAR(K$8)=2023,Inputs!$D$50,Inputs!$E$50)) -> 280.675 | ... AA35: =AA$14*(IF(YEAR(AA$8)=2023,Inputs!$D$50,Inputs!$E$50)) -> 203.203
B36: Japanese Restaurant | D36: =D$14*(IF(YEAR(D$8)=2023,Inputs!$D$55,Inputs!$E$55)) -> 195.7 | E36: =E$14*(IF(YEAR(E$8)=2023,Inputs!$D$55,Inputs!$E$55)) -> 199.82 | F36: =F$14*(IF(YEAR(F$8)=2023,Inputs!$D$55,Inputs!$E$55)) -> 203.94 | G36: =G$14*(IF(YEAR(G$8)=2023,Inputs!$D$55,Inputs!$E$55)) -> 208.06 | H36: =H$14*(IF(YEAR(H$8)=2023,Inputs!$D$55,Inputs!$E$55)) -> 212.18 | I36: =I$14*(IF(YEAR(I$8)=2023,Inputs!$D$55,Inputs!$E$55)) -> 216.3 | J36: =J$14*(IF(YEAR(J$8)=2023,Inputs!$D$55,Inputs!$E$55)) -> 220.42 | K36: =K$14*(IF(YEAR(K$8)=2023,Inputs!$D$55,Inputs!$E$55)) -> 224.54 | ... AA36: =AA$14*(IF(YEAR(AA$8)=2023,Inputs!$D$55,Inputs!$E$55)) -> 157.0205
B37: Burger Joint | D37: =D$14*(IF(YEAR(D$8)=2023,Inputs!$D$60,Inputs!$E$60)) -> 176.13 | E37: =E$14*(IF(YEAR(E$8)=2023,Inputs!$D$60,Inputs!$E$60)) -> 179.838 | F37: =F$14*(IF(YEAR(F$8)=2023,Inputs!$D$60,Inputs!$E$60)) -> 183.546 | G37: =G$14*(IF(YEAR(G$8)=2023,Inputs!$D$60,Inputs!$E$60)) -> 187.254 | H37: =H$14*(IF(YEAR(H$8)=2023,Inputs!$D$60,Inputs!$E$60)) -> 190.962 | I37: =I$14*(IF(YEAR(I$8)=2023,Inputs!$D$60,Inputs!$E$60)) -> 194.67 | J37: =J$14*(IF(YEAR(J$8)=2023,Inputs!$D$60,Inputs!$E$60)) -> 198.378 | K37: =K$14*(IF(YEAR(K$8)=2023,Inputs!$D$60,Inputs!$E$60)) -> 202.086 | ... AA37: =AA$14*(IF(YEAR(AA$8)=2023,Inputs!$D$60,Inputs!$E$60)) -> 166.257
B38: Pizzeria | D38: =D$14*IF(YEAR(D$8)=2023,Inputs!$D$65,Inputs!$E$65) -> 146.775 | E38: =E$14*IF(YEAR(E$8)=2023,Inputs!$D$65,Inputs!$E$65) -> 149.865 | F38: =F$14*IF(YEAR(F$8)=2023,Inputs!$D$65,Inputs!$E$65) -> 152.955 | G38: =G$14*IF(YEAR(G$8)=2023,Inputs!$D$65,Inputs!$E$65) -> 156.045 | H38: =H$14*IF(YEAR(H$8)=2023,Inputs!$D$65,Inputs!$E$65) -> 159.135 | I38: =I$14*IF(YEAR(I$8)=2023,Inputs!$D$65,Inputs!$E$65) -> 162.225 | J38: =J$14*IF(YEAR(J$8)=2023,Inputs!$D$65,Inputs!$E$65) -> 165.315 | K38: =K$14*IF(YEAR(K$8)=2023,Inputs!$D$65,Inputs!$E$65) -> 168.405 | ... AA38: =AA$14*IF(YEAR(AA$8)=2023,Inputs!$D$65,Inputs!$E$65) -> 138.5475
B39: Beverage Brand | D39: =D$14*IF(YEAR(D$8)=2023,Inputs!$D$70,Inputs!$E$70) -> 117.42 | E39: =E$14*IF(YEAR(E$8)=2023,Inputs!$D$70,Inputs!$E$70) -> 119.892 | F39: =F$14*IF(YEAR(F$8)=2023,Inputs!$D$70,Inputs!$E$70) -> 122.364 | G39: =G$14*IF(YEAR(G$8)=2023,Inputs!$D$70,Inputs!$E$70) -> 124.836 | H39: =H$14*IF(YEAR(H$8)=2023,Inputs!$D$70,Inputs!$E$70) -> 127.308 | I39: =I$14*IF(YEAR(I$8)=2023,Inputs!$D$70,Inputs!$E$70) -> 129.78 | J39: =J$14*IF(YEAR(J$8)=2023,Inputs!$D$70,Inputs!$E$70) -> 132.252 | K39: =K$14*IF(YEAR(K$8)=2023,Inputs!$D$70,Inputs!$E$70) -> 134.724 | ... AA39: =AA$14*IF(YEAR(AA$8)=2023,Inputs!$D$70,Inputs!$E$70) -> 120.0745
B40: Delivery Service | D40: =D$14*IF(YEAR(D$8)=2023,Inputs!$D$75,Inputs!$E$75) -> 97.85 | E40: =E$14*IF(YEAR(E$8)=2023,Inputs!$D$75,Inputs!$E$75) -> 99.91 | F40: =F$14*IF(YEAR(F$8)=2023,Inputs!$D$75,Inputs!$E$75) -> 101.97 | G40: =G$14*IF(YEAR(G$8)=2023,Inputs!$D$75,Inputs!$E$75) -> 104.03 | H40: =H$14*IF(YEAR(H$8)=2023,Inputs!$D$75,Inputs!$E$75) -> 106.09 | I40: =I$14*IF(YEAR(I$8)=2023,Inputs!$D$75,Inputs!$E$75) -> 108.15 | J40: =J$14*IF(YEAR(J$8)=2023,Inputs!$D$75,Inputs!$E$75) -> 110.21 | K40: =K$14*IF(YEAR(K$8)=2023,Inputs!$D$75,Inputs!$E$75) -> 112.27 | ... AA40: =AA$14*IF(YEAR(AA$8)=2023,Inputs!$D$75,Inputs!$E$75) -> 138.5475
B41: Central Kitchen (Commissary) | D41: =D$14*IF(YEAR(D$8)=2023,Inputs!$D$80,Inputs!$E$80) -> 0 | E41: =E$14*IF(YEAR(E$8)=2023,Inputs!$D$80,Inputs!$E$80) -> 0 | F41: =F$14*IF(YEAR(F$8)=2023,Inputs!$D$80,Inputs!$E$80) -> 0 | G41: =G$14*IF(YEAR(G$8)=2023,Inputs!$D$80,Inputs!$E$80) -> 0 | H41: =H$14*IF(YEAR(H$8)=2023,Inputs!$D$80,Inputs!$E$80) -> 0 | I41: =I$14*IF(YEAR(I$8)=2023,Inputs!$D$80,Inputs!$E$80) -> 0 | J41: =J$14*IF(YEAR(J$8)=2023,Inputs!$D$80,Inputs!$E$80) -> 0 | K41: =K$14*IF(YEAR(K$8)=2023,Inputs!$D$80,Inputs!$E$80) -> 0 | ... AA41: =AA$14*IF(YEAR(AA$8)=2023,Inputs!$D$80,Inputs!$E$80) -> 0
B42: Total Revenue | D42: =SUM(D35:D41) -> 978.5 | E42: =SUM(E35:E41) -> 999.1 | F42: =SUM(F35:F41) -> 1019.7 | G42: =SUM(G35:G41) -> 1040.3 | H42: =SUM(H35:H41) -> 1060.9 | I42: =SUM(I35:I41) -> 1081.5 | J42: =SUM(J35:J41) -> 1102.1 | K42: =SUM(K35:K41) -> 1122.7 | ... AA42: =SUM(AA35:AA41) -> 923.65
B44: COGS by Segment
B46: Italian Restaurant | D46: =D$15*(IF(YEAR(D$8)=2023,Inputs!$D$91,Inputs!$E$91)) -> -158.517 | E46: =E$15*(IF(YEAR(E$8)=2023,Inputs!$D$91,Inputs!$E$91)) -> -161.8542 | F46: =F$15*(IF(YEAR(F$8)=2023,Inputs!$D$91,Inputs!$E$91)) -> -165.1914 | G46: =G$15*(IF(YEAR(G$8)=2023,Inputs!$D$91,Inputs!$E$91)) -> -168.5286 | H46: =H$15*(IF(YEAR(H$8)=2023,Inputs!$D$91,Inputs!$E$91)) -> -171.8658 | I46: =I$15*(IF(YEAR(I$8)=2023,Inputs!$D$91,Inputs!$E$91)) -> -175.203 | J46: =J$15*(IF(YEAR(J$8)=2023,Inputs!$D$91,Inputs!$E$91)) -> -178.5402 | K46: =K$15*(IF(YEAR(K$8)=2023,Inputs!$D$91,Inputs!$E$91)) -> -181.8774 | ... AA46: =AA$15*(IF(YEAR(AA$8)=2023,Inputs!$D$91,Inputs!$E$91)) -> -138.5475
B47: Japanese Restaurant | D47: =D$15*(IF(YEAR(D$8)=2023,Inputs!$D$96,Inputs!$E$96)) -> -117.42 | E47: =E$15*(IF(YEAR(E$8)=2023,Inputs!$D$96,Inputs!$E$96)) -> -119.892 | F47: =F$15*(IF(YEAR(F$8)=2023,Inputs!$D$96,Inputs!$E$96)) -> -122.364 | G47: =G$15*(IF(YEAR(G$8)=2023,Inputs!$D$96,Inputs!$E$96)) -> -124.836 | H47: =H$15*(IF(YEAR(H$8)=2023,Inputs!$D$96,Inputs!$E$96)) -> -127.308 | I47: =I$15*(IF(YEAR(I$8)=2023,Inputs!$D$96,Inputs!$E$96)) -> -129.78 | J47: =J$15*(IF(YEAR(J$8)=2023,Inputs!$D$96,Inputs!$E$96)) -> -132.252 | K47: =K$15*(IF(YEAR(K$8)=2023,Inputs!$D$96,Inputs!$E$96)) -> -134.724 | ... AA47: =AA$15*(IF(YEAR(AA$8)=2023,Inputs!$D$96,Inputs!$E$96)) -> -99.7542
B48: Burger Joint | D48: =D$15*(IF(YEAR(D$8)=2023,Inputs!$D$101,Inputs!$E$101)) -> -105.678 | E48: =E$15*(IF(YEAR(E$8)=2023,Inputs!$D$101,Inputs!$E$101)) -> -107.9028 | F48: =F$15*(IF(YEAR(F$8)=2023,Inputs!$D$101,Inputs!$E$101)) -> -110.1276 | G48: =G$15*(IF(YEAR(G$8)=2023,Inputs!$D$101,Inputs!$E$101)) -> -112.3524 | H48: =H$15*(IF(YEAR(H$8)=2023,Inputs!$D$101,Inputs!$E$101)) -> -114.5772 | I48: =I$15*(IF(YEAR(I$8)=2023,Inputs!$D$101,Inputs!$E$101)) -> -116.802 | J48: =J$15*(IF(YEAR(J$8)=2023,Inputs!$D$101,Inputs!$E$101)) -> -119.0268 | K48: =K$15*(IF(YEAR(K$8)=2023,Inputs!$D$101,Inputs!$E$101)) -> -121.2516 | ... AA48: =AA$15*(IF(YEAR(AA$8)=2023,Inputs!$D$101,Inputs!$E$101)) -> -110.838
B49: Pizzeria | D49: =D$15*(IF(YEAR(D$8)=2023,Inputs!$D$106,Inputs!$E$106)) -> -82.194 | E49: =E$15*(IF(YEAR(E$8)=2023,Inputs!$D$106,Inputs!$E$106)) -> -83.9244 | F49: =F$15*(IF(YEAR(F$8)=2023,Inputs!$D$106,Inputs!$E$106)) -> -85.6548 | G49: =G$15*(IF(YEAR(G$8)=2023,Inputs!$D$106,Inputs!$E$106)) -> -87.3852 | H49: =H$15*(IF(YEAR(H$8)=2023,Inputs!$D$106,Inputs!$E$106)) -> -89.1156 | I49: =I$15*(IF(YEAR(I$8)=2023,Inputs!$D$106,Inputs!$E$106)) -> -90.846 | J49: =J$15*(IF(YEAR(J$8)=2023,Inputs!$D$106,Inputs!$E$106)) -> -92.5764 | K49: =K$15*(IF(YEAR(K$8)=2023,Inputs!$D$106,Inputs!$E$106)) -> -94.3068 | ... AA49: =AA$15*(IF(YEAR(AA$8)=2023,Inputs!$D$106,Inputs!$E$106)) -> -77.5866
B50: Beverage Brand | D50: =D$15*(IF(YEAR(D$8)=2023,Inputs!$D$111,Inputs!$E$111)) -> -52.839 | E50: =E$15*(IF(YEAR(E$8)=2023,Inputs!$D$111,Inputs!$E$111)) -> -53.9514 | F50: =F$15*(IF(YEAR(F$8)=2023,Inputs!$D$111,Inputs!$E$111)) -> -55.0638 | G50: =G$15*(IF(YEAR(G$8)=2023,Inputs!$D$111,Inputs!$E$111)) -> -56.1762 | H50: =H$15*(IF(YEAR(H$8)=2023,Inputs!$D$111,Inputs!$E$111)) -> -57.2886 | I50: =I$15*(IF(YEAR(I$8)=2023,Inputs!$D$111,Inputs!$E$111)) -> -58.401 | J50: =J$15*(IF(YEAR(J$8)=2023,Inputs!$D$111,Inputs!$E$111)) -> -59.5134 | K50: =K$15*(IF(YEAR(K$8)=2023,Inputs!$D$111,Inputs!$E$111)) -> -60.6258 | ... AA50: =AA$15*(IF(YEAR(AA$8)=2023,Inputs!$D$111,Inputs!$E$111)) -> -44.3352
B51: Delivery Service | D51: =D$15*(IF(YEAR(D$8)=2023,Inputs!$D$116,Inputs!$E$116)) -> -52.839 | E51: =E$15*(IF(YEAR(E$8)=2023,Inputs!$D$116,Inputs!$E$116)) -> -53.9514 | F51: =F$15*(IF(YEAR(F$8)=2023,Inputs!$D$116,Inputs!$E$116)) -> -55.0638 | G51: =G$15*(IF(YEAR(G$8)=2023,Inputs!$D$116,Inputs!$E$116)) -> -56.1762 | H51: =H$15*(IF(YEAR(H$8)=2023,Inputs!$D$116,Inputs!$E$116)) -> -57.2886 | I51: =I$15*(IF(YEAR(I$8)=2023,Inputs!$D$116,Inputs!$E$116)) -> -58.401 | J51: =J$15*(IF(YEAR(J$8)=2023,Inputs!$D$116,Inputs!$E$116)) -> -59.5134 | K51: =K$15*(IF(YEAR(K$8)=2023,Inputs!$D$116,Inputs!$E$116)) -> -60.6258 | ... AA51: =AA$15*(IF(YEAR(AA$8)=2023,Inputs!$D$116,Inputs!$E$116)) -> -66.5028
B52: Central Kitchen (Commissary) | D52: =D$15*(IF(YEAR(D$8)=2023,Inputs!$D$121,Inputs!$E$121)) -> -17.613 | E52: =E$15*(IF(YEAR(E$8)=2023,Inputs!$D$121,Inputs!$E$121)) -> -17.9838 | F52: =F$15*(IF(YEAR(F$8)=2023,Inputs!$D$121,Inputs!$E$121)) -> -18.3546 | G52: =G$15*(IF(YEAR(G$8)=2023,Inputs!$D$121,Inputs!$E$121)) -> -18.7254 | H52: =H$15*(IF(YEAR(H$8)=2023,Inputs!$D$121,Inputs!$E$121)) -> -19.0962 | I52: =I$15*(IF(YEAR(I$8)=2023,Inputs!$D$121,Inputs!$E$121)) -> -19.467 | J52: =J$15*(IF(YEAR(J$8)=2023,Inputs!$D$121,Inputs!$E$121)) -> -19.8378 | K52: =K$15*(IF(YEAR(K$8)=2023,Inputs!$D$121,Inputs!$E$121)) -> -20.2086 | ... AA52: =AA$15*(IF(YEAR(AA$8)=2023,Inputs!$D$121,Inputs!$E$121)) -> -16.6257
B53: Total COGS | D53: =SUM(D46:D52) -> -587.1 | E53: =SUM(E46:E52) -> -599.46 | F53: =SUM(F46:F52) -> -611.82 | G53: =SUM(G46:G52) -> -624.18 | H53: =SUM(H46:H52) -> -636.54 | I53: =SUM(I46:I52) -> -648.9 | J53: =SUM(J46:J52) -> -661.26 | K53: =SUM(K46:K52) -> -673.62 | ... AA53: =SUM(AA46:AA52) -> -554.19
B55: Gross Profit by Segment
B57: Italian Restaurant | D57: =D35+D46 -> 86.108 | E57: =E35+E46 -> 87.9208 | F57: =F35+F46 -> 89.7336 | G57: =G35+G46 -> 91.5464 | H57: =H35+H46 -> 93.3592 | I57: =I35+I46 -> 95.172 | J57: =J35+J46 -> 96.9848 | K57: =K35+K46 -> 98.7976 | ... AA57: =AA35+AA46 -> 64.6555
B58: Japanese Restaurant | D58: =D36+D47 -> 78.28 | E58: =E36+E47 -> 79.928 | F58: =F36+F47 -> 81.576 | G58: =G36+G47 -> 83.224 | H58: =H36+H47 -> 84.872 | I58: =I36+I47 -> 86.52 | J58: =J36+J47 -> 88.168 | K58: =K36+K47 -> 89.816 | ... AA58: =AA36+AA47 -> 57.2663
B59: Burger Joint | D59: =D37+D48 -> 70.452 | E59: =E37+E48 -> 71.9352 | F59: =F37+F48 -> 73.4184 | G59: =G37+G48 -> 74.9016 | H59: =H37+H48 -> 76.3848 | I59: =I37+I48 -> 77.868 | J59: =J37+J48 -> 79.3512 | K59: =K37+K48 -> 80.8344 | ... AA59: =AA37+AA48 -> 55.419
B60: Pizzeria | D60: =D38+D49 -> 64.581 | E60: =E38+E49 -> 65.9406 | F60: =F38+F49 -> 67.3002 | G60: =G38+G49 -> 68.6598 | H60: =H38+H49 -> 70.0194 | I60: =I38+I49 -> 71.379 | J60: =J38+J49 -> 72.7386 | K60: =K38+K49 -> 74.0982 | ... AA60: =AA38+AA49 -> 60.9609
B61: Beverage Brand | D61: =D39+D50 -> 64.581 | E61: =E39+E50 -> 65.9406 | F61: =F39+F50 -> 67.3002 | G61: =G39+G50 -> 68.6598 | H61: =H39+H50 -> 70.0194 | I61: =I39+I50 -> 71.379 | J61: =J39+J50 -> 72.7386 | K61: =K39+K50 -> 74.0982 | ... AA61: =AA39+AA50 -> 75.7393
B62: Delivery Service | D62: =D40+D51 -> 45.011 | E62: =E40+E51 -> 45.9586 | F62: =F40+F51 -> 46.9062 | G62: =G40+G51 -> 47.8538 | H62: =H40+H51 -> 48.8014 | I62: =I40+I51 -> 49.749 | J62: =J40+J51 -> 50.6966 | K62: =K40+K51 -> 51.6442 | ... AA62: =AA40+AA51 -> 72.0447
B63: Central Kitchen (Commissary) | D63: =D41+D52 -> -17.613 | E63: =E41+E52 -> -17.9838 | F63: =F41+F52 -> -18.3546 | G63: =G41+G52 -> -18.7254 | H63: =H41+H52 -> -19.0962 | I63: =I41+I52 -> -19.467 | J63: =J41+J52 -> -19.8378 | K63: =K41+K52 -> -20.2086 | ... AA63: =AA41+AA52 -> -16.6257
B64: Total Gross Profi | D64: =SUM(D57:D63) -> 391.4 | E64: =SUM(E57:E63) -> 399.64 | F64: =SUM(F57:F63) -> 407.88 | G64: =SUM(G57:G63) -> 416.12 | H64: =SUM(H57:H63) -> 424.36 | I64: =SUM(I57:I63) -> 432.6 | J64: =SUM(J57:J63) -> 440.84 | K64: =SUM(K57:K63) -> 449.08 | ... AA64: =SUM(AA57:AA63) -> 369.46
B66: Operation Expenses by Segment
B68: Italian Restaurant | D68: =D$20*(IF(YEAR(D$8)=2023,Inputs!$D$132,Inputs!$E$132)) -> -301.35 | E68: =E$20*(IF(YEAR(E$8)=2023,Inputs!$D$132,Inputs!$E$132)) -> -307.09 | F68: =F$20*(IF(YEAR(F$8)=2023,Inputs!$D$132,Inputs!$E$132)) -> -312.83 | G68: =G$20*(IF(YEAR(G$8)=2023,Inputs!$D$132,Inputs!$E$132)) -> -318.57 | H68: =H$20*(IF(YEAR(H$8)=2023,Inputs!$D$132,Inputs!$E$132)) -> -324.31 | I68: =I$20*(IF(YEAR(I$8)=2023,Inputs!$D$132,Inputs!$E$132)) -> -330.05 | J68: =J$20*(IF(YEAR(J$8)=2023,Inputs!$D$132,Inputs!$E$132)) -> -335.79 | K68: =K$20*(IF(YEAR(K$8)=2023,Inputs!$D$132,Inputs!$E$132)) -> -341.53 | ... AA68: =AA$20*(IF(YEAR(AA$8)=2023,Inputs!$D$132,Inputs!$E$132)) -> -408.304
B69: Japanese Restaurant | D69: =D$20*(IF(YEAR(D$8)=2023,Inputs!$D$137,Inputs!$E$137)) -> -215.25 | E69: =E$20*(IF(YEAR(E$8)=2023,Inputs!$D$137,Inputs!$E$137)) -> -219.35 | F69: =F$20*(IF(YEAR(F$8)=2023,Inputs!$D$137,Inputs!$E$137)) -> -223.45 | G69: =G$20*(IF(YEAR(G$8)=2023,Inputs!$D$137,Inputs!$E$137)) -> -227.55 | H69: =H$20*(IF(YEAR(H$8)=2023,Inputs!$D$137,Inputs!$E$137)) -> -231.65 | I69: =I$20*(IF(YEAR(I$8)=2023,Inputs!$D$137,Inputs!$E$137)) -> -235.75 | J69: =J$20*(IF(YEAR(J$8)=2023,Inputs!$D$137,Inputs!$E$137)) -> -239.85 | K69: =K$20*(IF(YEAR(K$8)=2023,Inputs!$D$137,Inputs!$E$137)) -> -243.95 | ... AA69: =AA$20*(IF(YEAR(AA$8)=2023,Inputs!$D$137,Inputs!$E$137)) -> -298.376
B70: Burger Joint | D70: =D$20*(IF(YEAR(D$8)=2023,Inputs!$D$142,Inputs!$E$142)) -> -182.9625 | E70: =E$20*(IF(YEAR(E$8)=2023,Inputs!$D$142,Inputs!$E$142)) -> -186.4475 | F70: =F$20*(IF(YEAR(F$8)=2023,Inputs!$D$142,Inputs!$E$142)) -> -189.9325 | G70: =G$20*(IF(YEAR(G$8)=2023,Inputs!$D$142,Inputs!$E$142)) -> -193.4175 | H70: =H$20*(IF(YEAR(H$8)=2023,Inputs!$D$142,Inputs!$E$142)) -> -196.9025 | I70: =I$20*(IF(YEAR(I$8)=2023,Inputs!$D$142,Inputs!$E$142)) -> -200.3875 | J70: =J$20*(IF(YEAR(J$8)=2023,Inputs!$D$142,Inputs!$E$142)) -> -203.8725 | K70: =K$20*(IF(YEAR(K$8)=2023,Inputs!$D$142,Inputs!$E$142)) -> -207.3575 | ... AA70: =AA$20*(IF(YEAR(AA$8)=2023,Inputs!$D$142,Inputs!$E$142)) -> -266.968
B71: Pizzeria | D71: =D$20*(IF(YEAR(D$8)=2023,Inputs!$D$147,Inputs!$E$147)) -> -150.675 | E71: =E$20*(IF(YEAR(E$8)=2023,Inputs!$D$147,Inputs!$E$147)) -> -153.545 | F71: =F$20*(IF(YEAR(F$8)=2023,Inputs!$D$147,Inputs!$E$147)) -> -156.415 | G71: =G$20*(IF(YEAR(G$8)=2023,Inputs!$D$147,Inputs!$E$147)) -> -159.285 | H71: =H$20*(IF(YEAR(H$8)=2023,Inputs!$D$147,Inputs!$E$147)) -> -162.155 | I71: =I$20*(IF(YEAR(I$8)=2023,Inputs!$D$147,Inputs!$E$147)) -> -165.025 | J71: =J$20*(IF(YEAR(J$8)=2023,Inputs!$D$147,Inputs!$E$147)) -> -167.895 | K71: =K$20*(IF(YEAR(K$8)=2023,Inputs!$D$147,Inputs!$E$147)) -> -170.765 | ... AA71: =AA$20*(IF(YEAR(AA$8)=2023,Inputs!$D$147,Inputs!$E$147)) -> -219.856
B72: Beverage Brand | D72: =D$20*(IF(YEAR(D$8)=2023,Inputs!$D$152,Inputs!$E$152)) -> -107.625 | E72: =E$20*(IF(YEAR(E$8)=2023,Inputs!$D$152,Inputs!$E$152)) -> -109.675 | F72: =F$20*(IF(YEAR(F$8)=2023,Inputs!$D$152,Inputs!$E$152)) -> -111.725 | G72: =G$20*(IF(YEAR(G$8)=2023,Inputs!$D$152,Inputs!$E$152)) -> -113.775 | H72: =H$20*(IF(YEAR(H$8)=2023,Inputs!$D$152,Inputs!$E$152)) -> -115.825 | I72: =I$20*(IF(YEAR(I$8)=2023,Inputs!$D$152,Inputs!$E$152)) -> -117.875 | J72: =J$20*(IF(YEAR(J$8)=2023,Inputs!$D$152,Inputs!$E$152)) -> -119.925 | K72: =K$20*(IF(YEAR(K$8)=2023,Inputs!$D$152,Inputs!$E$152)) -> -121.975 | ... AA72: =AA$20*(IF(YEAR(AA$8)=2023,Inputs!$D$152,Inputs!$E$152)) -> -157.04
B73: Delivery Service | D73: =D$20*(IF(YEAR(D$8)=2023,Inputs!$D$157,Inputs!$E$157)) -> -86.1 | E73: =E$20*(IF(YEAR(E$8)=2023,Inputs!$D$157,Inputs!$E$157)) -> -87.74 | F73: =F$20*(IF(YEAR(F$8)=2023,Inputs!$D$157,Inputs!$E$157)) -> -89.38 | G73: =G$20*(IF(YEAR(G$8)=2023,Inputs!$D$157,Inputs!$E$157)) -> -91.02 | H73: =H$20*(IF(YEAR(H$8)=2023,Inputs!$D$157,Inputs!$E$157)) -> -92.66 | I73: =I$20*(IF(YEAR(I$8)=2023,Inputs!$D$157,Inputs!$E$157)) -> -94.3 | J73: =J$20*(IF(YEAR(J$8)=2023,Inputs!$D$157,Inputs!$E$157)) -> -95.94 | K73: =K$20*(IF(YEAR(K$8)=2023,Inputs!$D$157,Inputs!$E$157)) -> -97.58 | ... AA73: =AA$20*(IF(YEAR(AA$8)=2023,Inputs!$D$157,Inputs!$E$157)) -> -188.448
B74: Central Kitchen (Commissary) | D74: =D$20*(IF(YEAR(D$8)=2023,Inputs!$D$162,Inputs!$E$162)) -> -32.2875 | E74: =E$20*(IF(YEAR(E$8)=2023,Inputs!$D$162,Inputs!$E$162)) -> -32.9025 | F74: =F$20*(IF(YEAR(F$8)=2023,Inputs!$D$162,Inputs!$E$162)) -> -33.5175 | G74: =G$20*(IF(YEAR(G$8)=2023,Inputs!$D$162,Inputs!$E$162)) -> -34.1325 | H74: =H$20*(IF(YEAR(H$8)=2023,Inputs!$D$162,Inputs!$E$162)) -> -34.7475 | I74: =I$20*(IF(YEAR(I$8)=2023,Inputs!$D$162,Inputs!$E$162)) -> -35.3625 | J74: =J$20*(IF(YEAR(J$8)=2023,Inputs!$D$162,Inputs!$E$162)) -> -35.9775 | K74: =K$20*(IF(YEAR(K$8)=2023,Inputs!$D$162,Inputs!$E$162)) -> -36.5925 | ... AA74: =AA$20*(IF(YEAR(AA$8)=2023,Inputs!$D$162,Inputs!$E$162)) -> -31.408
B75: Total Segment Operating Expenses | D75: =SUM(D68:D74) -> -1076.25 | E75: =SUM(E68:E74) -> -1096.75 | F75: =SUM(F68:F74) -> -1117.25 | G75: =SUM(G68:G74) -> -1137.75 | H75: =SUM(H68:H74) -> -1158.25 | I75: =SUM(I68:I74) -> -1178.75 | J75: =SUM(J68:J74) -> -1199.25 | K75: =SUM(K68:K74) -> -1219.75 | ... AA75: =SUM(AA68:AA74) -> -1570.4
B77: EBITDA by Segment
B79: Italian Restaurant | D79: =D57+D68 -> -215.242 | E79: =E57+E68 -> -219.1692 | F79: =F57+F68 -> -223.0964 | G79: =G57+G68 -> -227.0236 | H79: =H57+H68 -> -230.9508 | I79: =I57+I68 -> -234.878 | J79: =J57+J68 -> -238.8052 | K79: =K57+K68 -> -242.7324 | ... AA79: =AA57+AA68 -> -343.6485
B80: Japanese Restaurant | D80: =D58+D69 -> -136.97 | E80: =E58+E69 -> -139.422 | F80: =F58+F69 -> -141.874 | G80: =G58+G69 -> -144.326 | H80: =H58+H69 -> -146.778 | I80: =I58+I69 -> -149.23 | J80: =J58+J69 -> -151.682 | K80: =K58+K69 -> -154.134 | ... AA80: =AA58+AA69 -> -241.1097
B81: Burger Joint | D81: =D59+D70 -> -112.5105 | E81: =E59+E70 -> -114.5123 | F81: =F59+F70 -> -116.5141 | G81: =G59+G70 -> -118.5159 | H81: =H59+H70 -> -120.5177 | I81: =I59+I70 -> -122.5195 | J81: =J59+J70 -> -124.5213 | K81: =K59+K70 -> -126.5231 | ... AA81: =AA59+AA70 -> -211.549
B82: Pizzeria | D82: =D60+D71 -> -86.094 | E82: =E60+E71 -> -87.6044 | F82: =F60+F71 -> -89.1148 | G82: =G60+G71 -> -90.6252 | H82: =H60+H71 -> -92.1356 | I82: =I60+I71 -> -93.646 | J82: =J60+J71 -> -95.1564 | K82: =K60+K71 -> -96.6668 | ... AA82: =AA60+AA71 -> -158.8951
B83: Beverage Brand | D83: =D61+D72 -> -43.044 | E83: =E61+E72 -> -43.7344 | F83: =F61+F72 -> -44.4248 | G83: =G61+G72 -> -45.1152 | H83: =H61+H72 -> -45.8056 | I83: =I61+I72 -> -46.496 | J83: =J61+J72 -> -47.1864 | K83: =K61+K72 -> -47.8768 | ... AA83: =AA61+AA72 -> -81.3007
B84: Delivery Service | D84: =D62+D73 -> -41.089 | E84: =E62+E73 -> -41.7814 | F84: =F62+F73 -> -42.4738 | G84: =G62+G73 -> -43.1662 | H84: =H62+H73 -> -43.8586 | I84: =I62+I73 -> -44.551 | J84: =J62+J73 -> -45.2434 | K84: =K62+K73 -> -45.9358 | ... AA84: =AA62+AA73 -> -116.4033
B85: Central Kitchen (Commissary) | D85: =D63+D74 -> -49.9005 | E85: =E63+E74 -> -50.8863 | F85: =F63+F74 -> -51.8721 | G85: =G63+G74 -> -52.8579 | H85: =H63+H74 -> -53.8437 | I85: =I63+I74 -> -54.8295 | J85: =J63+J74 -> -55.8153 | K85: =K63+K74 -> -56.8011 | ... AA85: =AA63+AA74 -> -48.0337
B86: Total Segment EBITDA | D86: =SUM(D79:D85) -> -684.85 | E86: =SUM(E79:E85) -> -697.11 | F86: =SUM(F79:F85) -> -709.37 | G86: =SUM(G79:G85) -> -721.63 | H86: =SUM(H79:H85) -> -733.89 | I86: =SUM(I79:I85) -> -746.15 | J86: =SUM(J79:J85) -> -758.41 | K86: =SUM(K79:K85) -> -770.67 | ... AA86: =SUM(AA79:AA85) -> -1200.94
B88: Check Revenue Total | D88: =D14-D42 -> 0 | E88: =E14-E42 -> 0 | F88: =F14-F42 -> 0 | G88: =G14-G42 -> 0 | H88: =H14-H42 -> 0 | I88: =I14-I42 -> 0 | J88: =J14-J42 -> 0 | K88: =K14-K42 -> 0 | ... AA88: =AA14-AA42 -> 0
B89: Check COGS Total | D89: =D15-D53 -> 0 | E89: =E15-E53 -> 0 | F89: =F15-F53 -> 0 | G89: =G15-G53 -> 0 | H89: =H15-H53 -> 0 | I89: =I15-I53 -> 0 | J89: =J15-J53 -> 0 | K89: =K15-K53 -> 0 | ... AA89: =AA15-AA53 -> 0
B90: Check ExpensesTotal | D90: =D20-D75 -> 0 | E90: =E20-E75 -> 0 | F90: =F20-F75 -> 0 | G90: =G20-G75 -> 0 | H90: =H20-H75 -> 0 | I90: =I20-I75 -> 0 | J90: =J20-J75 -> 0 | K90: =K20-K75 -> 0 | ... AA90: =AA20-AA75 -> 0
B93: Cash Flow Statement
B95: CASH FROM OPERATIONS
B96: Net Income | D96: =D28 -> -613.33706 | E96: =E28 -> -641.23694 | F96: =F28 -> -661.13502 | G96: =G28 -> -683.03128 | H96: =H28 -> -704.92572 | I96: =I28 -> -726.81832 | J96: =J28 -> -748.70909 | K96: =K28 -> -770.598 | ... AA96: =AA28 -> -1408.6712
B97: Depreciation & Amortization | D97: =-D23 -> 41.666667 | E97: =-E23 -> 41.666667 | F97: =-F23 -> 41.666667 | G97: =-G23 -> 41.666667 | H97: =-H23 -> 41.666667 | I97: =-I23 -> 41.666667 | J97: =-J23 -> 41.666667 | K97: =-K23 -> 41.666667 | ... AA97: =-AA23 -> 41.666667
B98: Cash From Accounts Receivable | D98: =D224 -> -40.212329 | E98: =E224 -> -0.84657534 | F98: =F224 -> -0.84657534 | G98: =G224 -> -0.84657534 | H98: =H224 -> -0.84657534 | I98: =I224 -> -0.84657534 | J98: =J224 -> -0.84657534 | K98: =K224 -> -0.84657534 | ... AA98: =AA224 -> 0.41712329
B99: Cash From Inventory | D99: =D225 -> 16.084932 | E99: =E225 -> 0.33863014 | F99: =F225 -> 0.33863014 | G99: =G225 -> 0.33863014 | H99: =H225 -> 0.33863014 | I99: =I225 -> 0.33863014 | J99: =J225 -> 0.33863014 | K99: =K225 -> 0.33863014 | ... AA99: =AA225 -> -0.16684932
B100: Cash From Accounts Payable | D100: =D226 -> -32.169863 | E100: =E226 -> -0.67726027 | F100: =F226 -> -0.67726027 | G100: =G226 -> -0.67726027 | H100: =H226 -> -0.67726027 | I100: =I226 -> -0.67726027 | J100: =J226 -> -0.67726027 | K100: =K226 -> -0.67726027 | ... AA100: =AA226 -> 0.33369863
B101: Subtotal | D101: =SUM(D96:D100) -> -627.96765 | E101: =SUM(E96:E100) -> -600.75548 | F101: =SUM(F96:F100) -> -620.65355 | G101: =SUM(G96:G100) -> -642.54982 | H101: =SUM(H96:H100) -> -664.44426 | I101: =SUM(I96:I100) -> -686.33686 | J101: =SUM(J96:J100) -> -708.22763 | K101: =SUM(K96:K100) -> -730.11654 | ... AA101: =SUM(AA96:AA100) -> -1366.4206
B103: CASH FROM INVESTING
B104: Capital Expenditure | D104: =-(D$14*Inputs!$C$46) -> -48.925 | E104: =-(E$14*Inputs!$C$46) -> -49.955 | F104: =-(F$14*Inputs!$C$46) -> -50.985 | G104: =-(G$14*Inputs!$C$46) -> -52.015 | H104: =-(H$14*Inputs!$C$46) -> -53.045 | I104: =-(I$14*Inputs!$C$46) -> -54.075 | J104: =-(J$14*Inputs!$C$46) -> -55.105 | K104: =-(K$14*Inputs!$C$46) -> -56.135 | ... AA104: =-(AA$14*Inputs!$C$46) -> -46.1825
B105: Subtotal | D105: =D104 -> -48.925 | E105: =E104 -> -49.955 | F105: =F104 -> -50.985 | G105: =G104 -> -52.015 | H105: =H104 -> -53.045 | I105: =I104 -> -54.075 | J105: =J104 -> -55.105 | K105: =K104 -> -56.135 | ... AA105: =AA104 -> -46.1825
B107: Net Cash Flow before Revolver | D107: =D101+D105 -> -676.89265 | E107: =E101+E105 -> -650.71048 | F107: =F101+F105 -> -671.63855 | G107: =G101+G105 -> -694.56482 | H107: =H101+H105 -> -717.48926 | I107: =I101+I105 -> -740.41186 | J107: =J101+J105 -> -763.33263 | K107: =K101+K105 -> -786.25154 | ... AA107: =AA101+AA105 -> -1412.6031
B109: CASH FROM FINANCING
B110: Change in Long-Term Debt | D110: =D172 -> -71.843617 | E110: =E172 -> -72.203735 | F110: =F172 -> -72.565659 | G110: =G172 -> -72.929396 | H110: =H172 -> -73.294957 | I110: =I172 -> -73.66235 | J110: =J172 -> -74.031585 | K110: =K172 -> -74.402671 | ... AA110: =AA172 -> -80.599465
B111: Change in Revolving Credit Line | D111: =D200 -> 1748.7363 | E111: =E200 -> 722.91421 | F111: =F200 -> 744.20421 | G111: =G200 -> 767.49421 | H111: =H200 -> 790.78421 | I111: =I200 -> 814.07421 | J111: =J200 -> 837.36421 | K111: =K200 -> 860.65421 | ... AA111: =AA200 -> 0
B112: Subtotal | D112: =SUM(D110:D111) -> 1676.8927 | E112: =SUM(E110:E111) -> 650.71048 | F112: =SUM(F110:F111) -> 671.63855 | G112: =SUM(G110:G111) -> 694.56482 | H112: =SUM(H110:H111) -> 717.48926 | I112: =SUM(I110:I111) -> 740.41186 | J112: =SUM(J110:J111) -> 763.33263 | K112: =SUM(K110:K111) -> 786.25154 | ... AA112: =SUM(AA110:AA111) -> -80.599465
B114: CASH BALANCE
B115: Beginning Cash | D115: -500 | E115: =D117 -> 500 | F115: =E117 -> 500 | G115: =F117 -> 500 | H115: =G117 -> 500 | I115: =H117 -> 500 | J115: =I117 -> 500 | K115: =J117 -> 500 | L115: =K117 -> 500 | ... AA115: =Z117 -> -4713.0777
B116: Net Cash Flow after Revolver | D116: =D101+D105+D112 -> 1000 | E116: =E101+E105+E112 -> 0 | F116: =F101+F105+F112 -> 0 | G116: =G101+G105+G112 -> 0 | H116: =H101+H105+H112 -> 0 | I116: =I101+I105+I112 -> 0 | J116: =J101+J105+J112 -> 0 | K116: =K101+K105+K112 -> 0 | ... AA116: =AA101+AA105+AA112 -> -1493.2025
B117: Ending Cash | D117: =D115+D116 -> 500 | E117: =E115+E116 -> 500 | F117: =F115+F116 -> 500 | G117: =G115+G116 -> 500 | H117: =H115+H116 -> 500 | I117: =I115+I116 -> 500 | J117: =J115+J116 -> 500 | K117: =K115+K116 -> 500 | ... AA117: =AA115+AA116 -> -6206.2802
B122: Balance Sheet
B124: ASSETS
B126: Cash | D126: =D117 -> 500 | E126: =E117 -> 500 | F126: =F117 -> 500 | G126: =G117 -> 500 | H126: =H117 -> 500 | I126: =I117 -> 500 | J126: =J117 -> 500 | K126: =K117 -> 500 | ... AA126: =AA117 -> -6206.2802
B127: Accounts Receivable (AR) | D127: =D217 -> 40.212329 | E127: =E217 -> 41.058904 | F127: =F217 -> 41.905479 | G127: =G217 -> 42.752055 | H127: =H217 -> 43.59863 | I127: =I217 -> 44.445205 | J127: =J217 -> 45.291781 | K127: =K217 -> 46.138356 | ... AA127: =AA217 -> 37.958219
B128: Inventories | D128: =(Inputs!$C$45/365)*D$15 -> -16.084932 | E128: =(Inputs!$C$45/365)*E$15 -> -16.423562 | F128: =(Inputs!$C$45/365)*F$15 -> -16.762192 | G128: =(Inputs!$C$45/365)*G$15 -> -17.100822 | H128: =(Inputs!$C$45/365)*H$15 -> -17.439452 | I128: =(Inputs!$C$45/365)*I$15 -> -17.778082 | J128: =(Inputs!$C$45/365)*J$15 -> -18.116712 | K128: =(Inputs!$C$45/365)*K$15 -> -18.455342 | ... AA128: =(Inputs!$C$45/365)*AA$15 -> -15.183288
B129: Total Current Assets | D129: =SUM(D126:D128) -> 524.1274 | E129: =SUM(E126:E128) -> 524.63534 | F129: =SUM(F126:F128) -> 525.14329 | G129: =SUM(G126:G128) -> 525.65123 | H129: =SUM(H126:H128) -> 526.15918 | I129: =SUM(I126:I128) -> 526.66712 | J129: =SUM(J126:J128) -> 527.17507 | K129: =SUM(K126:K128) -> 527.68301 | ... AA129: =SUM(AA126:AA128) -> -6183.5053
B131: Property Plant & Equipment | D131: =Inputs!$C$33-D104+D23 -> 5007.2583 | E131: =D131-E104+E23 -> 5015.5467 | F131: =E131-F104+F23 -> 5024.865 | G131: =F131-G104+G23 -> 5035.2133 | H131: =G131-H104+H23 -> 5046.5917 | I131: =H131-I104+I23 -> 5059 | J131: =I131-J104+J23 -> 5072.4383 | K131: =J131-K104+K23 -> 5086.9067 | L131: =K131-L104+L23 -> 5102.405 | ... AA131: =Z131-AA104+AA23 -> 5263.5425
B134: Total Assets | D134: =D129+D131 -> 5531.3857 | E134: =E129+E131 -> 5540.182 | F134: =F129+F131 -> 5550.0083 | G134: =G129+G131 -> 5560.8646 | H134: =H129+H131 -> 5572.7508 | I134: =I129+I131 -> 5585.6671 | J134: =J129+J131 -> 5599.6134 | K134: =K129+K131 -> 5614.5897 | ... AA134: =AA129+AA131 -> -919.96276
B136: LIABILITIES
B138: Acounts Payable (AP) | D138: =(Inputs!$C$44/365)*D$15 -> -32.169863 | E138: =(Inputs!$C$44/365)*E$15 -> -32.847123 | F138: =(Inputs!$C$44/365)*F$15 -> -33.524384 | G138: =(Inputs!$C$44/365)*G$15 -> -34.201644 | H138: =(Inputs!$C$44/365)*H$15 -> -34.878904 | I138: =(Inputs!$C$44/365)*I$15 -> -35.556164 | J138: =(Inputs!$C$44/365)*J$15 -> -36.233425 | K138: =(Inputs!$C$44/365)*K$15 -> -36.910685 | ... AA138: =(Inputs!$C$44/365)*AA$15 -> -30.366575
B139: Revolving Credit Line | D139: =D201 -> 1748.7363 | E139: =E201 -> 2471.6505 | F139: =F201 -> 3215.8547 | G139: =G201 -> 3983.3489 | H139: =H201 -> 4774.1331 | I139: =I201 -> 5588.2073 | J139: =J201 -> 6425.5715 | K139: =K201 -> 7286.2258 | ... AA139: =AA201 -> 20000
B140: Total Current Liabilities | D140: =SUM(D138:D139) -> 1716.5664 | E140: =SUM(E138:E139) -> 2438.8034 | F140: =SUM(F138:F139) -> 3182.3303 | G140: =SUM(G138:G139) -> 3949.1473 | H140: =SUM(H138:H139) -> 4739.2542 | I140: =SUM(I138:I139) -> 5552.6512 | J140: =SUM(J138:J139) -> 6389.3381 | K140: =SUM(K138:K139) -> 7249.3151 | ... AA140: =SUM(AA138:AA139) -> 19969.633
B142: Long-Term Debt | D142: =D173 -> 4928.1564 | E142: =E173 -> 4855.9526 | F142: =F173 -> 4783.387 | G142: =G173 -> 4710.4576 | H142: =H173 -> 4637.1626 | I142: =I173 -> 4563.5003 | J142: =J173 -> 4489.4687 | K142: =K173 -> 4415.066 | ... AA142: =AA173 -> 3172.6089
...
